nimbletl/__init__.py
nimbletl/common/__init__.py
nimbletl/common/nimbletl_db.py
nimbletl/common/nimbletl_enum.py
nimbletl/common/nimbletl_exception.py
nimbletl/common/time_util.py
nimbletl/log_drive/__init__.py
nimbletl/log_drive/files.py
nimbletl/log_drive/log_drive_common.py
nimbletl/log_drive/log_drive_table.py
nimbletl/log_drive/time_windows.py
nimbletl/log_drive/upstream.py
nimbletl/log_drive/init/__init__.py
nimbletl/log_drive/init/cli.py
nimbletl/log_drive/init/init_drive_db.py
nimbletl/log_drive/init/load_config_to_env.py
tests/__init__.py
tests/test_log_drive.py
tests/tset.py
nimbletl-0.1.14.dist-info/METADATA
nimbletl-0.1.14.dist-info/WHEEL
nimbletl-0.1.14.dist-info/entry_points.txt
nimbletl-0.1.14.dist-info/top_level.txt
nimbletl-0.1.14.dist-info/RECORD
