Metadata-Version: 2.1
Name: nimbletl
Version: 0.1.14
Summary: Make your ETL easier and more nimble
Author: Ma Xiaoqiang
Author-email: 851788096@qq.com
Requires-Dist: click ==8.1.7
Requires-Dist: numpy ==1.26.4
Requires-Dist: pandas ==1.3.5
Requires-Dist: pymysql ==1.1.1
Requires-Dist: python-dateutil ==2.9.0.post0
Requires-Dist: pytz ==2024.1
Requires-Dist: pyyaml ==6.0.1
Requires-Dist: six ==1.16.0
Requires-Dist: sqlalchemy ==1.4.42
